claudefucker/__init__.py
claudefucker/cli.py
claudefucker/cli_setup.py
claudefucker/file_processor.py
claudefucker/format_converter.py
claudefucker/main.py
claudefucker/model_manager.py
claudefucker/models/__init__.py
claudefucker/models/base.py
claudefucker/models/deepseek.py
claudefucker/models/doubao.py
claudefucker/models/ernie.py
claudefucker/models/gemini.py
claudefucker/models/kimi.py
claudefucker/models/minimax.py
claudefucker/models/nvidia.py
claudefucker/models/ollama.py
claudefucker/models/openai.py
claudefucker/models/qwen.py
claudefucker/models/spark.py
claudefucker/models/yi.py
claudefucker/models/zhipu.py
claudefucker-3.4.0.dist-info/licenses/LICENSE
claudefucker-3.4.0.dist-info/METADATA
claudefucker-3.4.0.dist-info/WHEEL
claudefucker-3.4.0.dist-info/entry_points.txt
claudefucker-3.4.0.dist-info/top_level.txt
claudefucker-3.4.0.dist-info/RECORD
