Metadata-Version: 2.4
Name: claudefucker
Version: 3.4.0
Summary: Anthropic格式AI代理服务器 - 将Claude Code请求转换为各厂商格式
Author-email: python学霸 <contact@example.com>
Maintainer-email: python学霸 <contact@example.com>
License-Expression: MIT
Project-URL: Homepage, https://github.com/yourusername/claudefucker
Project-URL: Documentation, https://github.com/yourusername/claudefucker#readme
Project-URL: Repository, https://github.com/yourusername/claudefucker
Project-URL: Issues, https://github.com/yourusername/claudefucker/issues
Keywords: anthropic,claude,ai,llm,openai,api,proxy,server,flask,chatbot
Classifier: Development Status :: 4 - Beta
Classifier: Environment :: Web Environment
Classifier: Intended Audience :: Developers
Classifier: Operating System :: OS Independent
Classifier: Programming Language :: Python :: 3
Classifier: Programming Language :: Python :: 3.8
Classifier: Programming Language :: Python :: 3.9
Classifier: Programming Language :: Python :: 3.10
Classifier: Programming Language :: Python :: 3.11
Classifier: Programming Language :: Python :: 3.12
Classifier: Topic :: Internet :: WWW/HTTP :: HTTP Servers
Classifier: Topic :: Software Development :: Libraries :: Python Modules
Requires-Python: >=3.8
License-File: LICENSE
Requires-Dist: flask>=3.0.0
Requires-Dist: flask-cors>=4.0.0
Requires-Dist: openai>=1.0.0
Requires-Dist: anthropic>=0.7.0
Requires-Dist: zhipuai>=2.0.0
Requires-Dist: dashscope>=1.14.0
Requires-Dist: google-generativeai>=0.3.0
Requires-Dist: pyyaml>=6.0
Requires-Dist: colorama>=0.4.6
Requires-Dist: python-dotenv>=1.0.0
Requires-Dist: requests>=2.31.0
Provides-Extra: dev
Requires-Dist: build; extra == "dev"
Requires-Dist: twine; extra == "dev"
Requires-Dist: pytest>=7.0.0; extra == "dev"
Dynamic: license-file
